mbslave/__init__.py
mbslave/replication.py
mbslave/sql/CalculateRelatedTags.sql
mbslave/sql/CreateCollateIndexes.sql
mbslave/sql/CreateCollations.sql
mbslave/sql/CreateConstraints.sql
mbslave/sql/CreateFKConstraints.sql
mbslave/sql/CreateFunctions.sql
mbslave/sql/CreateIndexes.sql
mbslave/sql/CreateMirrorIndexes.sql
mbslave/sql/CreateMirrorOnlyFunctions.sql
mbslave/sql/CreateMirrorOnlyTriggers.sql
mbslave/sql/CreatePrimaryKeys.sql
mbslave/sql/CreateReplicationTriggers.sql
mbslave/sql/CreateReplicationTriggers2.sql
mbslave/sql/CreateSearchConfiguration.sql
mbslave/sql/CreateSearchIndexes.sql
mbslave/sql/CreateTables.sql
mbslave/sql/CreateTriggers.sql
mbslave/sql/CreateTypes.sql
mbslave/sql/CreateViews.sql
mbslave/sql/DisableLastUpdatedTriggers.sql
mbslave/sql/DropAll.sql
mbslave/sql/DropCollateIndexes.sql
mbslave/sql/DropCollations.sql
mbslave/sql/DropFKConstraints.sql
mbslave/sql/DropFunctions.sql
mbslave/sql/DropIndexes.sql
mbslave/sql/DropMirrorOnlyFunctions.sql
mbslave/sql/DropMirrorOnlyTriggers.sql
mbslave/sql/DropPrimaryKeys.sql
mbslave/sql/DropReplicationTriggers.sql
mbslave/sql/DropReplicationTriggers2.sql
mbslave/sql/DropSearchIndexes.sql
mbslave/sql/DropTables.sql
mbslave/sql/DropTriggers.sql
mbslave/sql/DropTypes.sql
mbslave/sql/DropViews.sql
mbslave/sql/EnableLastUpdatedTriggers.sql
mbslave/sql/Extensions.sql
mbslave/sql/InsertDefaultRows.sql
mbslave/sql/InsertTestData.sql
mbslave/sql/ReplicationSetup.sql
mbslave/sql/SetSequences.sql
mbslave/sql/TruncateTables.sql
mbslave/sql/caa/CreateEditFKConstraints.sql
mbslave/sql/caa/CreateFKConstraints.sql
mbslave/sql/caa/CreateFunctions.sql
mbslave/sql/caa/CreateIndexes.sql
mbslave/sql/caa/CreateMQTriggers.sql
mbslave/sql/caa/CreatePrimaryKeys.sql
mbslave/sql/caa/CreateReplicationTriggers.sql
mbslave/sql/caa/CreateReplicationTriggers2.sql
mbslave/sql/caa/CreateTables.sql
mbslave/sql/caa/CreateTriggers.sql
mbslave/sql/caa/CreateViews.sql
mbslave/sql/caa/DropFKConstraints.sql
mbslave/sql/caa/DropFunctions.sql
mbslave-28.0.0.dist-info/LICENSE
mbslave-28.0.0.dist-info/METADATA
mbslave-28.0.0.dist-info/WHEEL
mbslave-28.0.0.dist-info/entry_points.txt
mbslave-28.0.0.dist-info/RECORD
