Metadata-Version: 2.1
Name: mbslave
Version: 28.0.0
Summary: MusicBrainz Database Mirror
License: MIT
Author: Lukáš Lalinský
Author-email: lalinsky@gmail.com
Requires-Python: >=3.7,<4.0
Classifier: License :: OSI Approved :: MIT License
Classifier: Programming Language :: Python :: 3
Classifier: Programming Language :: Python :: 3.7
Classifier: Programming Language :: Python :: 3.8
Classifier: Programming Language :: Python :: 3.9
Classifier: Programming Language :: Python :: 3.10
Classifier: Programming Language :: Python :: 3.11
Requires-Dist: psycopg2 (>=2.9.2,<3.0.0)
Requires-Dist: six (>=1.16.0,<2.0.0)
